week_7/dffhigh.v
module dffhigh(clk, rst, d, q);
  input clk;
  input rst;   // asynchronous active-high reset
  input d;
  output reg q;

  always @(posedge clk or posedge rst) begin
    if (rst)
      q = 1'b0;
    else
      q = d;
  end
endmodule

week_7/dffhigh_tb.v
`timescale 1ns/1ns
`include "dffhigh.v"

module dffhigh_tb;
  reg clk, rst, d;
  wire q;

  dffhigh uut(clk, rst, d, q);

  // Clock generation
  initial clk = 0;
  always #5 clk = ~clk; // 10ns clock period

  initial begin
    $dumpfile("dffhigh_tb.vcd");  // VCD file for GTKWave
    $dumpvars(0, dffhigh_tb);

    // Test sequence
    rst = 1; d = 0; #10;  // Apply reset
    rst = 0; d = 1; #10;
    d = 0; #10;
    d = 1; #10;
    rst = 1; #10;          // Reset again
    rst = 0; d = 0; #20;

    $finish;
  end
endmodule

week_7/dffhigh_tb.vcd
$date
	Tue Oct 14 22:32:06 2025
$end
$version
	Icarus Verilog
$end
$timescale
	1ns
$end
$scope module dffhigh_tb $end
$var wire 1 ! q $end
$var reg 1 " clk $end
$var reg 1 # d $end
$var reg 1 $ rst $end
$scope module uut $end
$var wire 1 " clk $end
$var wire 1 # d $end
$var wire 1 $ rst $end
$var reg 1 ! q $end
$upscope $end
$upscope $end
$enddefinitions $end
$comment Show the parameter values. $end
$dumpall
$end
#0
$dumpvars
1$
0#
0"
0!
$end
#5
1"
#10
0"
1#
0$
#15
1!
1"
#20
0"
0#
#25
0!
1"
#30
0"
1#
#35
1!
1"
#40
0!
0"
1$
#45
1"
#50
0"
0#
0$
