week_7/jkffsync.v
module jkffsync(clk, rst, j, k, q);
  input clk;
  input rst;   // synchronous active-high reset
  input j, k;
  output reg q;

  always @(posedge clk) begin
    if (rst)
      q = 1'b0;        // synchronous reset
    else begin
      case ({j, k})
        2'b00: q = q;      // no change
        2'b01: q = 1'b0;   // reset
        2'b10: q = 1'b1;   // set
        2'b11: q = ~q;     // toggle
      endcase
    end
  end
endmodule

week_7/jkffsync_tb.v
`timescale 1ns/1ns
`include "jkffsync.v"

module jkffsync_tb;
  reg clk, rst, j, k;
  wire q;

  jkffsync uut(clk, rst, j, k, q);

  // Clock generation
  initial clk = 0;
  always #5 clk = ~clk; // 10ns period

  initial begin
    $dumpfile("jkffsync_tb.vcd");
    $dumpvars(0, jkffsync_tb);

    // Test sequence
    rst = 1; j = 0; k = 0; #10;  // synchronous reset
    rst = 0; j = 1; k = 0; #10;  // set
    j = 0; k = 1; #10;            // reset
    j = 1; k = 1; #10;            // toggle
    j = 0; k = 0; #10;            // no change
    j = 1; k = 1; #10;            // toggle
    $finish;
  end
endmodule

week_7/jkffsync_tb.vcd
$date
	Tue Oct 14 22:37:43 2025
$end
$version
	Icarus Verilog
$end
$timescale
	1ns
$end
$scope module jkffsync_tb $end
$var wire 1 ! q $end
$var reg 1 " clk $end
$var reg 1 # j $end
$var reg 1 $ k $end
$var reg 1 % rst $end
$scope module uut $end
$var wire 1 " clk $end
$var wire 1 # j $end
$var wire 1 $ k $end
$var wire 1 % rst $end
$var reg 1 ! q $end
$upscope $end
$upscope $end
$enddefinitions $end
$comment Show the parameter values. $end
$dumpall
$end
#0
$dumpvars
1%
0$
0#
0"
x!
$end
#5
0!
1"
#10
0"
1#
0%
#15
1!
1"
#20
0"
1$
0#
#25
0!
1"
#30
0"
1#
#35
1!
1"
#40
0"
0$
0#
#45
1"
#50
0"
1$
1#
#55
0!
1"
