week_7/tfflow.v
module tfflow(clk, rst, t, q);
  input clk;
  input rst;   // asynchronous active-low reset
  input t;
  output reg q;

  always @(negedge clk or negedge rst) begin
    if (!rst)
      q = 1'b0;        // reset is active low
    else if (t)
      q = ~q;          // toggle on T=1
  end
endmodule

week_7/tfflow_tb.v
`timescale 1ns/1ns
`include "tfflow.v"

module tfflow_tb;
  reg clk, rst, t;
  wire q;

  tfflow uut(clk, rst, t, q);

  // Clock generation
  initial clk = 0;
  always #5 clk = ~clk; // 10ns period

  initial begin
    $dumpfile("tfflow_tb.vcd");
    $dumpvars(0, tfflow_tb);

    // Test sequence
    rst = 0; t = 0; #10;   // Apply reset (active low)
    rst = 1; t = 1; #10;   // Toggle
    t = 0; #10;
    t = 1; #10;
    rst = 0; #10;           // Reset again
    rst = 1; t = 1; #20;    // Toggle
    $finish;
  end
endmodule

week_7/tfflow_tb.vcd
$date
	Tue Oct 14 22:35:02 2025
$end
$version
	Icarus Verilog
$end
$timescale
	1ns
$end
$scope module tfflow_tb $end
$var wire 1 ! q $end
$var reg 1 " clk $end
$var reg 1 # rst $end
$var reg 1 $ t $end
$scope module uut $end
$var wire 1 " clk $end
$var wire 1 # rst $end
$var wire 1 $ t $end
$var reg 1 ! q $end
$upscope $end
$upscope $end
$enddefinitions $end
$comment Show the parameter values. $end
$dumpall
$end
#0
$dumpvars
0$
0#
0"
0!
$end
#5
1"
#10
1!
0"
1$
1#
#15
1"
#20
0"
0$
#25
1"
#30
0!
0"
1$
#35
1"
#40
0"
0#
#45
1"
#50
1!
0"
1#
#55
1"
#60
0!
0"
#65
1"
#70
1!
0"
