dec2to4two.v
// 2-to-4 Decoder with active-high enable and active-low outputs
module dec2to4two(en, a, y);
  input en;
  input [1:0] a;
  output reg [3:0] y;

  always @ (en or a) 
  begin
    if (en) 
    begin
      case(a)
        2'b00: y = 4'b1110;  // Active-low output
        2'b01: y = 4'b1101;
        2'b10: y = 4'b1011;
        2'b11: y = 4'b0111;
      endcase
    end
    else 
      y = 4'b1111;       
  end
endmodule

dec2to4two_tb.v
`timescale 1ns/1ns
`include "dec2to4two.v"

module dec2to4two_tb;
  reg en;            
  reg [1:0] a;       
  wire [3:0] y;      
  dec2to4two uut(en, a, y);

  initial 
  begin
    $dumpfile("dec2to4two_tb.vcd");  // VCD file for GTKWave
    $dumpvars(0, dec2to4two_tb);

    
    en = 0; a = 2'b00; #10;
    a = 2'b01; #10;
    a = 2'b10; #10;
    a = 2'b11; #10;

    
    en = 1; a = 2'b00; #10;  // y = 1110
    a = 2'b01; #10;          // y = 1101
    a = 2'b10; #10;          // y = 1011
    a = 2'b11; #10;          // y = 0111

    
    en = 0; a = 2'b10; #10;  // y = 1111

    $finish;
  end
endmodule

dec2to4two_tb.vcd
$date
	Wed Sep 24 14:50:42 2025
$end
$version
	Icarus Verilog
$end
$timescale
	1ns
$end
$scope module dec2to4two_tb $end
$var wire 4 ! y [3:0] $end
$var reg 2 " a [1:0] $end
$var reg 1 # en $end
$scope module uut $end
$var wire 2 $ a [1:0] $end
$var wire 1 # en $end
$var reg 4 % y [3:0] $end
$upscope $end
$upscope $end
$enddefinitions $end
#0
$dumpvars
b1111 %
b0 $
0#
b0 "
b1111 !
$end
#10
b1 "
b1 $
#20
b10 "
b10 $
#30
b11 "
b11 $
#40
b1110 !
b1110 %
b0 "
b0 $
1#
#50
b1101 !
b1101 %
b1 "
b1 $
#60
b1011 !
b1011 %
b10 "
b10 $
#70
b111 !
b111 %
b11 "
b11 $
#80
b1111 !
b1111 %
b10 "
b10 $
0#
