dec2to4.v
module dec2to4(en, a, y);
  input en;
  input [1:0] a;
  output reg [3:0] y;

  always @ (en or a) 
  begin
    if (en) 
    begin
      if (a == 2'b00) 
      	y = 4'b0001;
      else if (a == 2'b01) 
      	y = 4'b0010;
      else if (a == 2'b10) 
      	y = 4'b0100;
      else 
      	y = 4'b1000;
    end 
    else 
      y = 4'b0000;
  end
endmodule

dec3to8.v
`include "dec2to4.v"
module dec3to8(en, a, y);
  input en;
  input [2:0] a;
  output [7:0] y;

  wire [3:0] y_low, y_high;

  dec2to4 d0(en & ~a[2], a[1:0], y_low);  
  dec2to4 d1(en & a[2], a[1:0], y_high);  

  assign y = {y_high, y_low};
endmodule

dec3to8_tb.v
`timescale 1ns/1ns
`include "dec3to8.v"

module dec3to8_tb;
  reg en;
  reg [2:0] a;
  wire [7:0] y;

  dec3to8 uut(en, a, y);

  initial 
  begin
    $dumpfile("dec3to8_tb.vcd");
    $dumpvars(0, dec3to8_tb);

    en = 0; a = 3'b000; #10;
    en = 1; a = 3'b000; #10;
    a = 3'b001; #10;
    a = 3'b010; #10;
    a = 3'b011; #10;
    a = 3'b100; #10;
    a = 3'b101; #10;
    a = 3'b110; #10;
    a = 3'b111; #10;
    en = 0; a = 3'b101; #10;

    $finish;
  end
endmodule

dec3to8_tb.vcd
$date
	Wed Sep 10 16:18:21 2025
$end
$version
	Icarus Verilog
$end
$timescale
	1ns
$end
$scope module dec3to8_tb $end
$var wire 8 ! y [7:0] $end
$var reg 3 " a [2:0] $end
$var reg 1 # en $end
$scope module uut $end
$var wire 3 $ a [2:0] $end
$var wire 1 # en $end
$var wire 4 % y_low [3:0] $end
$var wire 4 & y_high [3:0] $end
$var wire 8 ' y [7:0] $end
$scope module d0 $end
$var wire 2 ( a [1:0] $end
$var wire 1 ) en $end
$var reg 4 * y [3:0] $end
$upscope $end
$scope module d1 $end
$var wire 2 + a [1:0] $end
$var wire 1 , en $end
$var reg 4 - y [3:0] $end
$upscope $end
$upscope $end
$upscope $end
$enddefinitions $end
#0
$dumpvars
b0 -
0,
b0 +
b0 *
0)
b0 (
b0 '
b0 &
b0 %
b0 $
0#
b0 "
b0 !
$end
#10
b1 !
b1 '
b1 %
b1 *
1)
1#
#20
b10 !
b10 '
b10 %
b10 *
b1 (
b1 +
b1 "
b1 $
#30
b100 !
b100 '
b100 %
b100 *
b10 (
b10 +
b10 "
b10 $
#40
b1000 !
b1000 '
b1000 %
b1000 *
b11 (
b11 +
b11 "
b11 $
#50
0)
b1 &
b1 -
b10000 !
b10000 '
b0 %
b0 *
1,
b0 (
b0 +
b100 "
b100 $
#60
b100000 !
b100000 '
b10 &
b10 -
b1 (
b1 +
b101 "
b101 $
#70
b1000000 !
b1000000 '
b100 &
b100 -
b10 (
b10 +
b110 "
b110 $
#80
b10000000 !
b10000000 '
b1000 &
b1000 -
b11 (
b11 +
b111 "
b111 $
#90
b0 !
b0 '
b0 &
b0 -
b1 (
b1 +
0,
b101 "
b101 $
0#
