dec3to8two.v
module dec3to8two(w,en,y);
	input[2:0]w;
	input en;
	output reg [7:0]y;
	integer k;
	always @(en or w)
	begin
		for(k=0;k<=7;k=k+1)
			if((w==k)&&(en==1))
				y[k]=1;
			else
				y[k]=0;
	end
endmodule

dec4to16.v
`include "dec3to8two.v"

module dec4to16(w, en, y);
  input [3:0] w;         
  input en;              
  output [15:0] y;       

  wire [7:0] y_low, y_high;

  // Lower block active when MSB (w[3]) = 0
  dec3to8two d0(w[2:0], en & ~w[3], y_low);

  // Upper block active when MSB (w[3]) = 1
  dec3to8two d1(w[2:0], en & w[3], y_high);

  // Combine outputs: y_high is the upper 8 bits, y_low is the lower 8 bits
  assign y = {y_high, y_low};
endmodule

dec4to16_tb.v
`timescale 1ns/1ns
`include "dec4to16.v"

module dec4to16_tb;
  reg [3:0] w;            // 4-bit input
  reg en;                  // Enable signal
  wire [15:0] y;           // 16-bit output

  // Instantiate the 4-to-16 decoder
  dec4to16 uut(w, en, y);

  initial 
  begin
    $dumpfile("dec4to16_tb.vcd");   // VCD file for waveform
    $dumpvars(0, dec4to16_tb);

    
    en = 0; w = 4'b0000; #10;
    en = 1;
    w = 4'b0000; #10;
    w = 4'b0001; #10;
    w = 4'b0010; #10;
    w = 4'b0011; #10;
    w = 4'b0100; #10;
    w = 4'b0101; #10;
    w = 4'b0110; #10;
    w = 4'b0111; #10;
    w = 4'b1000; #10;
    w = 4'b1001; #10;
    w = 4'b1010; #10;
    w = 4'b1011; #10;
    w = 4'b1100; #10;
    w = 4'b1101; #10;
    w = 4'b1110; #10;
    w = 4'b1111; #10;

    en = 0; w = 4'b1010; #10;

    $finish;
  end
endmodule

dec4to16_tb.vcd
$date
	Wed Sep 24 14:26:01 2025
$end
$version
	Icarus Verilog
$end
$timescale
	1ns
$end
$scope module dec4to16_tb $end
$var wire 16 ! y [15:0] $end
$var reg 1 " en $end
$var reg 4 # w [3:0] $end
$scope module uut $end
$var wire 1 " en $end
$var wire 4 $ w [3:0] $end
$var wire 8 % y_low [7:0] $end
$var wire 8 & y_high [7:0] $end
$var wire 16 ' y [15:0] $end
$scope module d0 $end
$var wire 1 ( en $end
$var wire 3 ) w [2:0] $end
$var reg 8 * y [7:0] $end
$var integer 32 + k [31:0] $end
$upscope $end
$scope module d1 $end
$var wire 1 , en $end
$var wire 3 - w [2:0] $end
$var reg 8 . y [7:0] $end
$var integer 32 / k [31:0] $end
$upscope $end
$upscope $end
$upscope $end
$enddefinitions $end
#0
$dumpvars
b1000 /
b0 .
b0 -
0,
b1000 +
b0 *
b0 )
0(
b0 '
b0 &
b0 %
b0 $
b0 #
0"
b0 !
$end
#10
b1 !
b1 '
b1 %
b1 *
b1000 +
1(
1"
#20
b10 !
b10 '
b10 %
b10 *
b1000 +
b1000 /
b1 )
b1 -
b1 #
b1 $
#30
b100 !
b100 '
b100 %
b100 *
b1000 +
b1000 /
b10 )
b10 -
b10 #
b10 $
#40
b1000 !
b1000 '
b1000 %
b1000 *
b1000 +
b1000 /
b11 )
b11 -
b11 #
b11 $
#50
b10000 !
b10000 '
b10000 %
b10000 *
b1000 +
b1000 /
b100 )
b100 -
b100 #
b100 $
#60
b100000 !
b100000 '
b100000 %
b100000 *
b1000 +
b1000 /
b101 )
b101 -
b101 #
b101 $
#70
b1000000 !
b1000000 '
b1000000 %
b1000000 *
b1000 +
b1000 /
b110 )
b110 -
b110 #
b110 $
#80
b10000000 !
b10000000 '
b10000000 %
b10000000 *
b1000 +
b1000 /
b111 )
b111 -
b111 #
b111 $
#90
0(
b0 %
b0 *
b1000 +
b100000000 !
b100000000 '
b1 &
b1 .
b1000 /
1,
b0 )
b0 -
b1000 #
b1000 $
#100
b1000 +
b1000000000 !
b1000000000 '
b10 &
b10 .
b1000 /
b1 )
b1 -
b1001 #
b1001 $
#110
b1000 +
b10000000000 !
b10000000000 '
b100 &
b100 .
b1000 /
b10 )
b10 -
b1010 #
b1010 $
#120
b1000 +
b100000000000 !
b100000000000 '
b1000 &
b1000 .
b1000 /
b11 )
b11 -
b1011 #
b1011 $
#130
b1000 +
b1000000000000 !
b1000000000000 '
b10000 &
b10000 .
b1000 /
b100 )
b100 -
b1100 #
b1100 $
#140
b1000 +
b10000000000000 !
b10000000000000 '
b100000 &
b100000 .
b1000 /
b101 )
b101 -
b1101 #
b1101 $
#150
b1000 +
b100000000000000 !
b100000000000000 '
b1000000 &
b1000000 .
b1000 /
b110 )
b110 -
b1110 #
b1110 $
#160
b1000 +
b1000000000000000 !
b1000000000000000 '
b10000000 &
b10000000 .
b1000 /
b111 )
b111 -
b1111 #
b1111 $
#170
b1000 +
b0 !
b0 '
b0 &
b0 .
b1000 /
b10 )
b10 -
0,
b1010 #
b1010 $
0"
