priority16to4.v
// 16-to-4 Priority Encoder using for loop
module priority16to4(w, y, valid);
  input [15:0] w;       
  output reg [3:0] y;  
  output reg valid;     

  integer i;

  always @ (w)
  begin
    y = 4'b0000;       // Default output
    valid = 0;          // Default valid signal

    
    for (i = 15; i >= 0; i = i - 1)
    begin
      if (w[i] == 1'b1)
      begin
        y = i[3:0];     // Assign index as output
        valid = 1;      // Set valid high
      end
    end
  end
endmodule

priority16to4_tb.v
`timescale 1ns/1ns
`include "priority16to4.v"

module priority16to4_tb;
  reg [15:0] w;          
  wire [3:0] y;          
  wire valid;            

  
  priority16to4 uut(w, y, valid);

  initial 
  begin
    $dumpfile("priority16to4_tb.vcd");
    $dumpvars(0, priority16to4_tb);

    // No input active
    w = 16'b0000_0000_0000_0000; #10;

    // Test single inputs
    w = 16'b0000_0000_0000_0001; #10;  // Position 0
    w = 16'b0000_0000_0000_1000; #10;  // Position 3
    w = 16'b0000_0001_0000_0000; #10;  // Position 8
    w = 16'b1000_0000_0000_0000; #10;  // Position 15 (highest priority)

    // Test multiple inputs to check priority
    w = 16'b0100_0000_0000_0001; #10;  // 14 vs 0 -> Output = 14
    w = 16'b0010_0000_1000_0000; #10;  // 13 vs 7 -> Output = 13
    w = 16'b0001_0000_0000_1111; #10;  // 12 vs lower bits -> Output = 12

    // Reset again
    w = 16'b0000_0000_0000_0000; #10;

    $finish;
  end
endmodule

priority16to4_tb.vcd
$date
	Wed Sep 24 15:24:13 2025
$end
$version
	Icarus Verilog
$end
$timescale
	1ns
$end
$scope module priority16to4_tb $end
$var wire 4 ! y [3:0] $end
$var wire 1 " valid $end
$var reg 16 # w [15:0] $end
$scope module uut $end
$var wire 16 $ w [15:0] $end
$var reg 1 " valid $end
$var reg 4 % y [3:0] $end
$var integer 32 & i [31:0] $end
$upscope $end
$upscope $end
$enddefinitions $end
#0
$dumpvars
b11111111111111111111111111111111 &
b0 %
b0 $
b0 #
0"
b0 !
$end
#10
1"
b11111111111111111111111111111111 &
b1 #
b1 $
#20
b11 !
b11 %
b11111111111111111111111111111111 &
1"
b1000 #
b1000 $
#30
b11111111111111111111111111111111 &
1"
b1000 !
b1000 %
b100000000 #
b100000000 $
#40
b11111111111111111111111111111111 &
1"
b1111 !
b1111 %
b1000000000000000 #
b1000000000000000 $
#50
b11111111111111111111111111111111 &
1"
b0 !
b0 %
b100000000000001 #
b100000000000001 $
#60
b111 !
b111 %
b11111111111111111111111111111111 &
1"
b10000010000000 #
b10000010000000 $
#70
b11111111111111111111111111111111 &
1"
b0 !
b0 %
b1000000001111 #
b1000000001111 $
#80
b11111111111111111111111111111111 &
0"
b0 #
b0 $
