priority4to2.v
// 4-to-2 Priority Encoder using casex
module priority4to2(w, y, valid);
  input [3:0] w;        
  output reg [1:0] y;   
  output reg valid;     

  always @ (w) 
  begin
    casex(w)
      4'b1xxx: begin   // Highest priority: w[3]
        y = 2'b11;
        valid = 1;
      end
      4'b01xx: begin   // Next priority: w[2]
        y = 2'b10;
        valid = 1;
      end
      4'b001x: begin   // Next priority: w[1]
        y = 2'b01;
        valid = 1;
      end
      4'b0001: begin   // Lowest priority: w[0]
        y = 2'b00;
        valid = 1;
      end
      default: begin   // No inputs active
        y = 2'b00;
        valid = 0;
      end
    endcase
  end
endmodule

priority4to2_tb.v
`timescale 1ns/1ns
`include "priority4to2.v"

module priority4to2_tb;
  reg [3:0] w;          
  wire [1:0] y;         
  wire valid;           

  
  priority4to2 uut(w, y, valid);

  initial 
  begin
    $dumpfile("priority4to2_tb.vcd");
    $dumpvars(0, priority4to2_tb);

   
    w = 4'b0000; #10;  // No inputs active
    w = 4'b0001; #10;  // Only w[0] active
    w = 4'b0010; #10;  // Only w[1] active
    w = 4'b0100; #10;  // Only w[2] active
    w = 4'b1000; #10;  // Only w[3] active

    // Multiple inputs active (priority check)
    w = 4'b1010; #10;  // w[3] & w[1] active -> priority w[3]
    w = 4'b0111; #10;  // w[2], w[1], w[0] active -> priority w[2]
    w = 4'b0011; #10;  // w[1], w[0] active -> priority w[1]

    $finish;
  end
endmodule

priority4to2_tb.vcd
$date
	Wed Sep 24 15:13:13 2025
$end
$version
	Icarus Verilog
$end
$timescale
	1ns
$end
$scope module priority4to2_tb $end
$var wire 2 ! y [1:0] $end
$var wire 1 " valid $end
$var reg 4 # w [3:0] $end
$scope module uut $end
$var wire 4 $ w [3:0] $end
$var reg 1 " valid $end
$var reg 2 % y [1:0] $end
$upscope $end
$upscope $end
$enddefinitions $end
#0
$dumpvars
b0 %
b0 $
b0 #
0"
b0 !
$end
#10
1"
b1 #
b1 $
#20
b1 !
b1 %
b10 #
b10 $
#30
b10 !
b10 %
b100 #
b100 $
#40
b11 !
b11 %
b1000 #
b1000 $
#50
b1010 #
b1010 $
#60
b10 !
b10 %
b111 #
b111 $
#70
b1 !
b1 %
b11 #
b11 $
