week10/asy4up.v
module asy4up (clear, clk, Q);
input clear, clk;
output [3:0] Q;
reg [3:0] Q;

always @ (negedge clear or posedge clk)
begin
  if (!clear)
    Q <= 4'b0000;          // Resets counter
  else
    Q[0] <= ~Q[0];         // Toggles LSB
end

always @ (posedge Q[0])
  Q[1] <= ~Q[1];

always @ (posedge Q[1])
  Q[2] <= ~Q[2];

always @ (posedge Q[2])
  Q[3] <= ~Q[3];

endmodule

week10/asy4up_tb.v
`timescale 1ns/1ns
`include "asy4up.v"

module asy4up_tb;
reg clk, clear;
wire [3:0] Q;

asy4up uut(clear, clk, Q);

initial begin
  $dumpfile("asy4up_tb.vcd");
  $dumpvars(0, asy4up_tb);
  clk = 0; clear = 0;
  #5 clear = 1;             // Release reset
  #200 $finish;             // Run simulation
end

always #5 clk = ~clk;       // Clock with 10ns period

initial begin
  $monitor("Time=%0t | Q=%b", $time, Q);
end
endmodule

week10/asy4up_tb.vcd
$date
	Wed Oct 29 15:00:45 2025
$end
$version
	Icarus Verilog
$end
$timescale
	1ns
$end
$scope module asy4up_tb $end
$var wire 4 ! Q [3:0] $end
$var reg 1 " clear $end
$var reg 1 # clk $end
$scope module uut $end
$var wire 1 " clear $end
$var wire 1 # clk $end
$var reg 4 $ Q [3:0] $end
$upscope $end
$upscope $end
$enddefinitions $end
#0
$dumpvars
b0 $
0#
0"
b0 !
$end
#5
b1111 !
b1111 $
1#
1"
#10
0#
#15
b1110 !
b1110 $
1#
#20
0#
#25
b1101 !
b1101 $
1#
#30
0#
#35
b1100 !
b1100 $
1#
#40
0#
#45
b1011 !
b1011 $
1#
#50
0#
#55
b1010 !
b1010 $
1#
#60
0#
#65
b1001 !
b1001 $
1#
#70
0#
#75
b1000 !
b1000 $
1#
#80
0#
#85
b111 !
b111 $
1#
#90
0#
#95
b110 !
b110 $
1#
#100
0#
#105
b101 !
b101 $
1#
#110
0#
#115
b100 !
b100 $
1#
#120
0#
#125
b11 !
b11 $
1#
#130
0#
#135
b10 !
b10 $
1#
#140
0#
#145
b1 !
b1 $
1#
#150
0#
#155
b0 !
b0 $
1#
#160
0#
#165
b1111 !
b1111 $
1#
#170
0#
#175
b1110 !
b1110 $
1#
#180
0#
#185
b1101 !
b1101 $
1#
#190
0#
#195
b1100 !
b1100 $
1#
#200
0#
#205
b1011 !
b1011 $
1#
