week10/ring4bit.v
module ring4bit(clear, clk, Q);
input clear, clk;
output [3:0] Q;
reg [3:0] temp;

always @ (posedge clk or negedge clear)
begin
  if (!clear)
    temp <= 4'b0001;           // Initial state
  else
    temp <= {temp[2:0], temp[3]}; // Rotate left
end

assign Q = temp;
endmodule


module tff (Q, T, clear, clk);
input T, clear, clk;
output reg Q;
always @ (posedge clk or negedge clear)
begin
  if (clear == 0)
    Q <= 0;
  else if (T == 1)
    Q <= ~Q;
  else
    Q <= Q;
end
endmodule

week10/ring4bit_tb.v
`timescale 1ns/1ns
`include "ring4bit.v"

module ring4bit_tb;
reg clk, clear;
wire [3:0] Q;

ring4bit uut(clear, clk, Q);

initial begin
  $dumpfile("ring4bit_tb.vcd");
  $dumpvars(0, ring4bit_tb);
  clk = 0; clear = 0;
  #5 clear = 1;
  #100 $finish;
end

always #5 clk = ~clk;

initial begin
  $monitor("Time=%0t | Q=%b", $time, Q);
end
endmodule

week10/ring4bit_tb.vcd
$date
	Wed Oct 29 14:13:09 2025
$end
$version
	Icarus Verilog
$end
$timescale
	1ns
$end
$scope module ring4bit_tb $end
$var wire 4 ! Q [3:0] $end
$var reg 1 " clear $end
$var reg 1 # clk $end
$scope module uut $end
$var wire 4 $ Q [3:0] $end
$var wire 1 " clear $end
$var wire 1 # clk $end
$var reg 4 % temp [3:0] $end
$upscope $end
$upscope $end
$enddefinitions $end
#0
$dumpvars
b1 %
b1 $
0#
0"
b1 !
$end
#5
b10 !
b10 $
b10 %
1#
1"
#10
0#
#15
b100 !
b100 $
b100 %
1#
#20
0#
#25
b1000 !
b1000 $
b1000 %
1#
#30
0#
#35
b1 !
b1 $
b1 %
1#
#40
0#
#45
b10 !
b10 $
b10 %
1#
#50
0#
#55
b100 !
b100 $
b100 %
1#
#60
0#
#65
b1000 !
b1000 $
b1000 %
1#
#70
0#
#75
b1 !
b1 $
b1 %
1#
#80
0#
#85
b10 !
b10 $
b10 %
1#
#90
0#
#95
b100 !
b100 $
b100 %
1#
#100
0#
#105
b1000 !
b1000 $
b1000 %
1#
